porridge/__init__.py
porridge/_ffi.so
porridge/_ffi_build.py
porridge/exceptions.py
porridge/porridge.py
porridge/utils.py
porridge-1.0.0.dist-info/DESCRIPTION.rst
porridge-1.0.0.dist-info/METADATA
porridge-1.0.0.dist-info/RECORD
porridge-1.0.0.dist-info/WHEEL
porridge-1.0.0.dist-info/metadata.json
porridge-1.0.0.dist-info/top_level.txt
